gitdump/__init__.py
gitdump/__main__.py
gitdump/func.py
gitdump-1.0.2.dist-info/METADATA
gitdump-1.0.2.dist-info/WHEEL
gitdump-1.0.2.dist-info/entry_points.txt
gitdump-1.0.2.dist-info/top_level.txt
gitdump-1.0.2.dist-info/RECORD
